luxafor/__init__.py
luxafor/discovery.py
luxafor_base/__init__.py
luxafor_base/const.py
luxafor_base/model.py
luxafor_ble/__init__.py
luxafor_ble/const.py
luxafor_ble/data.py
luxafor_ble/dot.py
luxafor_ble/scanner.py
luxafor_usb/__init__.py
luxafor_usb/const.py
luxafor_usb/data.py
luxafor_usb/flag.py
python_luxafor-0.0.2.dist-info/LICENSE
python_luxafor-0.0.2.dist-info/METADATA
python_luxafor-0.0.2.dist-info/WHEEL
python_luxafor-0.0.2.dist-info/top_level.txt
python_luxafor-0.0.2.dist-info/RECORD
