Metadata-Version: 2.1
Name: python-luxafor
Version: 0.0.2
Summary: Python API for Luxafor busylights
Author-email: Matt Lizzie <matt@lizzie.pro>
License: MIT License
Project-URL: Homepage, https://github.com/koswolf/python-luxafor
Classifier: Development Status :: 2 - Pre-Alpha
Classifier: Intended Audience :: Developers
Classifier: License :: OSI Approved :: MIT License
Classifier: Natural Language :: English
Classifier: Programming Language :: Python :: 3.5
Requires-Python: >=3.7
License-File: LICENSE
Requires-Dist: bleak (>=0.19.5)
Requires-Dist: bleak-retry-connector (>=2.13.0)
Requires-Dist: pyusb (>=1.0.0)
Provides-Extra: dev
Requires-Dist: pre-commit (==2.15.0) ; extra == 'dev'
Requires-Dist: bumpversion (==0.6.0) ; extra == 'dev'
Requires-Dist: bandit (==1.7.4) ; extra == 'dev'
Requires-Dist: black (==23.1.0) ; extra == 'dev'
Requires-Dist: codespell (==2.2.2) ; extra == 'dev'
Requires-Dist: isort (==5.12.0) ; extra == 'dev'
Requires-Dist: pylint (==2.17.1) ; extra == 'dev'
Requires-Dist: ruff (==0.0.256) ; extra == 'dev'
Requires-Dist: yamllint (==1.28.0) ; extra == 'dev'
Requires-Dist: twine (==4.0.2) ; extra == 'dev'
